<annotation>
	<folder>Fungus Gnats - Fruitfly</folder>
	<filename>14571224822_5ba0a745ce_b.jpg</filename>
	<path>E:\Projects\Freelancing\Insects in agriculture\Data\Fungus Gnats - Fruitfly-20210307T140406Z-001\Fungus Gnats - Fruitfly\14571224822_5ba0a745ce_b.jpg</path>
	<source>
		<database>Unknown</database>
	</source>
	<size>
		<width>1024</width>
		<height>750</height>
		<depth>3</depth>
	</size>
	<segmented>0</segmented>
	<object>
		<name>Fruit fly</name>
		<pose>Unspecified</pose>
		<truncated>0</truncated>
		<difficult>0</difficult>
		<bndbox>
			<xmin>156</xmin>
			<ymin>20</ymin>
			<xmax>957</xmax>
			<ymax>711</ymax>
		</bndbox>
	</object>
</annotation>
