<annotation>
	<folder>Tobacco Whitefly</folder>
	<filename>319a.jpg</filename>
	<path>E:\Projects\Freelancing\Insects in agriculture\Data\Tobacco Whitefly-20210306T201259Z-001\Tobacco Whitefly\319a.jpg</path>
	<source>
		<database>Unknown</database>
	</source>
	<size>
		<width>600</width>
		<height>389</height>
		<depth>3</depth>
	</size>
	<segmented>0</segmented>
	<object>
		<name>Tobacco Whitefly</name>
		<pose>Unspecified</pose>
		<truncated>0</truncated>
		<difficult>0</difficult>
		<bndbox>
			<xmin>236</xmin>
			<ymin>117</ymin>
			<xmax>385</xmax>
			<ymax>290</ymax>
		</bndbox>
	</object>
</annotation>
