<annotation>
	<folder>aphids</folder>
	<filename>5501002.jpg</filename>
	<path>E:\Projects\Freelancing\Insects in agriculture\aphids\5501002.jpg</path>
	<source>
		<database>Unknown</database>
	</source>
	<size>
		<width>768</width>
		<height>510</height>
		<depth>3</depth>
	</size>
	<segmented>0</segmented>
	<object>
		<name>Aphids</name>
		<pose>Unspecified</pose>
		<truncated>0</truncated>
		<difficult>0</difficult>
		<bndbox>
			<xmin>266</xmin>
			<ymin>197</ymin>
			<xmax>427</xmax>
			<ymax>310</ymax>
		</bndbox>
	</object>
</annotation>
