<annotation>
	<folder>Spodoptera (worm,armyworm)</folder>
	<filename>images29.jpg</filename>
	<path>E:\Projects\Freelancing\Insects in agriculture\Data\Spodoptera (worm,armyworm)-20210308T142528Z-001\Spodoptera (worm,armyworm)\images29.jpg</path>
	<source>
		<database>Unknown</database>
	</source>
	<size>
		<width>290</width>
		<height>174</height>
		<depth>3</depth>
	</size>
	<segmented>0</segmented>
	<object>
		<name>Armyworm</name>
		<pose>Unspecified</pose>
		<truncated>0</truncated>
		<difficult>0</difficult>
		<bndbox>
			<xmin>26</xmin>
			<ymin>45</ymin>
			<xmax>251</xmax>
			<ymax>138</ymax>
		</bndbox>
	</object>
</annotation>
